Metadata-Version: 2.1
Name: quartet-capture
Version: 4.0.0
Summary: A capture and queuing interface for QU4RTET.
Home-page: https://gitlab.com/serial-lab/quartet_capture
Author: Rob Magee
Author-email: slab@serial-lab.com
License: GPLv3
Keywords: quartet_capture QU4RTET EPCIS open-source
Platform: UNKNOWN
Classifier: Development Status :: 5 - Production/Stable
Classifier: Framework :: Django
Classifier: Framework :: Django :: 2.0
Classifier: Intended Audience :: Healthcare Industry
Classifier: Intended Audience :: Manufacturing
Classifier: Intended Audience :: Developers
Classifier: License :: OSI Approved :: GNU General Public License v3 (GPLv3)
Classifier: Natural Language :: English
Classifier: Programming Language :: Python :: 3
Classifier: Programming Language :: Python :: 3.5
Classifier: Programming Language :: Python :: 3.6
Requires-Dist: haikunator
